emlx/__init__.py
emlx/emlx.py
emlx-1.0.4.dist-info/LICENSE
emlx-1.0.4.dist-info/METADATA
emlx-1.0.4.dist-info/WHEEL
emlx-1.0.4.dist-info/top_level.txt
emlx-1.0.4.dist-info/RECORD
