Metadata-Version: 2.1
Name: emlx
Version: 1.0.4
Summary: The leightweight parser for emlx files.
Home-page: https://github.com/mikez/emlx
Author: Michael Belfrage
Author-email: consulting@belfrage.net
License: MIT
Project-URL: Code, https://github.com/mikez/emlx
Project-URL: Issue tracker, https://github.com/mikez/emlx/issues
Platform: UNKNOWN
Classifier: License :: OSI Approved :: MIT License
Classifier: Operating System :: OS Independent
Classifier: Programming Language :: Python :: 3
Requires-Python: >=3.6
